{
  "ownKey": "index",
  "childrenPages": {"meta": {
    "ownKey": "meta",
    "ownPages": [
      {
        "reference": {
          "path": "meta",
          "baseUrl": "https://github.com/Quentus123/Comy",
          "fileName": "assets.index",
          "extension": "json",
          "usePrettyUrl": false,
          "link": "https://github.com/Quentus123/Comy/meta/assets.index.json"
        },
        "description": "",
        "title": "Assets . Index"
      },
      {
        "reference": {
          "path": "meta",
          "baseUrl": "https://github.com/Quentus123/Comy",
          "fileName": "changelog.index",
          "extension": "json",
          "usePrettyUrl": false,
          "link": "https://github.com/Quentus123/Comy/meta/changelog.index.json"
        },
        "description": "",
        "title": "Changelog . Index"
      },
      {
        "reference": {
          "path": "meta",
          "baseUrl": "https://github.com/Quentus123/Comy",
          "fileName": "forms.index",
          "extension": "json",
          "usePrettyUrl": false,
          "link": "https://github.com/Quentus123/Comy/meta/forms.index.json"
        },
        "description": "",
        "title": "Forms . Index"
      },
      {
        "reference": {
          "path": "meta",
          "baseUrl": "https://github.com/Quentus123/Comy",
          "fileName": "home.index",
          "extension": "json",
          "usePrettyUrl": false,
          "link": "https://github.com/Quentus123/Comy/meta/home.index.json"
        },
        "description": "",
        "title": "Home . Index"
      },
      {
        "reference": {
          "path": "meta",
          "baseUrl": "https://github.com/Quentus123/Comy",
          "fileName": "kotlindoc.index",
          "extension": "json",
          "usePrettyUrl": false,
          "link": "https://github.com/Quentus123/Comy/meta/kotlindoc.index.json"
        },
        "description": "",
        "title": "Kotlindoc . Index"
      },
      {
        "reference": {
          "path": "meta",
          "baseUrl": "https://github.com/Quentus123/Comy",
          "fileName": "pages.index",
          "extension": "json",
          "usePrettyUrl": false,
          "link": "https://github.com/Quentus123/Comy/meta/pages.index.json"
        },
        "description": "",
        "title": "Pages . Index"
      },
      {
        "reference": {
          "path": "meta",
          "baseUrl": "https://github.com/Quentus123/Comy",
          "fileName": "wiki.index",
          "extension": "json",
          "usePrettyUrl": false,
          "link": "https://github.com/Quentus123/Comy/meta/wiki.index.json"
        },
        "description": "",
        "title": "Wiki . Index"
      },
      {
        "reference": {
          "path": "meta",
          "baseUrl": "https://github.com/Quentus123/Comy",
          "fileName": "sitemap.index",
          "extension": "json",
          "usePrettyUrl": false,
          "link": "https://github.com/Quentus123/Comy/meta/sitemap.index.json"
        },
        "description": "",
        "title": "Sitemap . Index"
      },
      {
        "reference": {
          "path": "meta",
          "baseUrl": "https://github.com/Quentus123/Comy",
          "fileName": "indices.index",
          "extension": "json",
          "usePrettyUrl": false,
          "link": "https://github.com/Quentus123/Comy/meta/indices.index.json"
        },
        "description": "",
        "title": "Indices . Index"
      },
      {
        "reference": {
          "path": "meta",
          "baseUrl": "https://github.com/Quentus123/Comy",
          "fileName": "all.index",
          "extension": "json",
          "usePrettyUrl": false,
          "link": "https://github.com/Quentus123/Comy/meta/all.index.json"
        },
        "description": "",
        "title": "All . Index"
      }
    ]
  }}
}